<?xml version="1.0" encoding="utf-8"?>
  <exercise template="Phrasebank" category="Meetings">
   <title>
    <![CDATA[<b>Talking about differences</b>]]>
    </title>
    <dialogue>
      <sentence name="A">[What's the difference between the old mobile and the new mobile?]</sentence>
      <sentence name="B">The new mobile is smaller and it has a different battery.</sentence>
	  <transfer>What's the difference between xxx and xxx?</transfer>
	</dialogue>
    <dialogue>
      <sentence name="A">There are two mobiles on sale. [How do they compare?]</sentence>
      <sentence name="B">The Nokia phone has a better battery but the other phone has a bigger screen.</sentence>
	  <transfer>How do they compare?</transfer>
	 </dialogue>
     <dialogue>
      <sentence name="A">What do you think of the Nokia mobiles? [Are they better than our mobiles?]</sentence>
      <sentence name="B">Yes, they are. They're a lot better.</sentence>
	  <transfer>Are they better than xxx?</transfer>
	  </dialogue>
     <dialogue>
      <sentence name="A">Is there a difference between the German supplier and the US supplier?</sentence>
      <sentence name="B">[The German supplier is cheaper.]</sentence>
	  <transfer>xxx is cheaper.</transfer>
	  </dialogue>
     <dialogue>
      <sentence name="A">Is there a difference between the German supplier and the US supplier?</sentence>
      <sentence name="B">[The US supplier is more expensive.]</sentence>
	  <transfer>xxx is more expensive.</transfer>
	  </dialogue>
     <dialogue>
      <sentence name="A">[The advantage of this office building is that it's near the airport.]</sentence>
      <sentence name="B">That's very important.</sentence>
	  <transfer>The advantage of xxx is ...</transfer>
	  </dialogue>
     <dialogue>
      <sentence name="A">[The disadvantage of this office building is that it's not in the city centre.]</sentence>
      <sentence name="B">That's a problem.</sentence>
      <transfer>The disadvantage of xxx is ...</transfer>
	  </dialogue>
  </exercise>