<?xml version="1.0" encoding="UTF-8" standalone="no"?>
<exercise>
  <rubric></rubric>
  <audio>data/1_content/listening/listening115.mp3</audio>
  <text>
    <![CDATA[<heading>62</heading>
      
      <p>1</p>
      <p><b>Receptionist</b> Good evening, madam.</p>
      <p><b> Jenny</b> Hello. My name is Chiang. I have a reservation for tonight.</p>
      <p><b>Receptionist</b> That's right. Can I see your credit card, please?</p>
      <p><b>Jenny</b> Here you are.</p>
      <p><b>Receptionist</b> Thank you. Your room is on the fifth floor. Room five-oh-one. The lift is over there.</p>
      <p><b>Jenny</b> Thanks. What time is breakfast served?</p>
      <p><b>Receptionist</b> It's between five and ten a.m. There's also dinner in the hotel restaurant this evening until ten.</p>
      <p><b>Jenny</b> Do I need to book a table?</p>
      <p><b>Receptionist</b> No, you don't.</p>
      <p>2</p>
      <p><b>Receptionist</b> Hello. Reception.</p>
      <p><b>Jenny</b> Hello. This is Ms Chiang in room five-oh-one. Can I have a wake-up call, please?</p>
      <p><b>Receptionist</b> Certainly. What time is that for?</p>
      <p><b>Jenny</b> Six a.m., please. Also, can you order me a taxi to the airport terminal for seven o'clock?</p>
      <p><b>Receptionist</b> Yes, we can arrange that.</p>
      <p><b>Jenny</b> Sorry, there's one other thing. Do the rooms have Internet access? I can't log on.</p>
      <p><b>Receptionist</b> Yes, they do, but there's a problem with the connection this evening. Sorry, we're trying to fix it now.</p>
      <p><b>Jenny</b> OK. I'd also like dinner in my room. Do you have room service?</p>
      <p><b>Receptionist</b> Yes, one moment, please ...</p>]]>
  </text>
</exercise>
